stanza/__init__.py
stanza/cli.py
stanza/context.py
stanza/device.py
stanza/exceptions.py
stanza/models.py
stanza/pyvisa.py
stanza/registry.py
stanza/timing.py
stanza/utils.py
stanza/analysis/__init__.py
stanza/analysis/criterion.py
stanza/analysis/fitting.py
stanza/analysis/preprocessing.py
stanza/base/__init__.py
stanza/base/channels.py
stanza/base/instruments.py
stanza/base/mixins.py
stanza/base/protocols.py
stanza/base/registry.py
stanza/configs/devices/device.sample.groups.yaml
stanza/configs/devices/device.sample.yaml
stanza/configs/templates/qua_config.json
stanza/drivers/__init__.py
stanza/drivers/opx.py
stanza/drivers/qdac2.py
stanza/drivers/qswitch.py
stanza/drivers/utils.py
stanza/jupyter/__init__.py
stanza/jupyter/core.py
stanza/jupyter/logs.py
stanza/jupyter/startup.py
stanza/jupyter/utils.py
stanza/logger/__init__.py
stanza/logger/data_logger.py
stanza/logger/datatypes.py
stanza/logger/session.py
stanza/logger/writers/__init__.py
stanza/logger/writers/base.py
stanza/logger/writers/bokeh_writer.py
stanza/logger/writers/hdf5_writer.py
stanza/logger/writers/jsonl_writer.py
stanza/plotter/__init__.py
stanza/plotter/backends/__init__.py
stanza/plotter/backends/bokeh.py
stanza/plotter/backends/inline.py
stanza/plotter/backends/server.py
stanza/plotter/backends/utils.py
stanza/routines/__init__.py
stanza/routines/core.py
stanza/routines/builtins/__init__.py
stanza/routines/builtins/health_check.py
stanza/routines/builtins/setup.py
stanza/routines/builtins/utils.py
stanza/routines/builtins/dqd_search/__init__.py
stanza/routines/builtins/dqd_search/grid_search.py
stanza/routines/builtins/dqd_search/routine.py
stanza/routines/builtins/dqd_search/utils.py
cq_stanza-0.5.0.dist-info/METADATA
cq_stanza-0.5.0.dist-info/WHEEL
cq_stanza-0.5.0.dist-info/entry_points.txt
cq_stanza-0.5.0.dist-info/licenses/LICENSE
cq_stanza-0.5.0.dist-info/RECORD
