Metadata-Version: 2.4
Name: cq-stanza
Version: 0.5.0
Summary: Stanza, build tune up sequences for quantum computers fast. Easy to code. Easy to run.
Project-URL: Homepage, https://github.com/conductorquantum/stanza
Project-URL: Repository, https://github.com/conductorquantum/stanza
Project-URL: Documentation, https://github.com/conductorquantum/stanza#readme
Project-URL: Bug Reports, https://github.com/conductorquantum/stanza/issues
Project-URL: Source Code, https://github.com/conductorquantum/stanza
Author-email: Brandon Severin <brandon@conductorquantum.com>, Joel Pendleton <joel@conductorquantum.com>, Raymond Jow <raymond@conductorquantum.com>
Maintainer-email: Brandon Severin <brandon@conductorquantum.com>, Joel Pendleton <joel@conductorquantum.com>, Raymond Jow <raymond@conductorquantum.com>
License: The MIT License (MIT)
License-File: LICENSE
Keywords: stanza
Classifier: Development Status :: 3 - Alpha
Classifier: Intended Audience :: Developers
Classifier: License :: OSI Approved :: MIT License
Classifier: Programming Language :: Python :: 3
Classifier: Programming Language :: Python :: 3.11
Classifier: Programming Language :: Python :: 3.12
Classifier: Programming Language :: Python :: 3.13
Classifier: Topic :: Software Development :: Libraries :: Python Modules
Requires-Python: >=3.11
Requires-Dist: bokeh>=3.0.0
Requires-Dist: click>=8.0.0
Requires-Dist: conductorquantum>=0.1.2
Requires-Dist: h5py>=3.8.0
Requires-Dist: numpy>=1.24.0
Requires-Dist: pydantic>=2.11.7
Requires-Dist: pyyaml>=6.0.2
Provides-Extra: dev
Requires-Dist: black>=23.0.0; extra == 'dev'
Requires-Dist: mypy>=1.0.0; extra == 'dev'
Requires-Dist: pre-commit>=3.0.0; extra == 'dev'
Requires-Dist: pytest-cov>=4.0.0; extra == 'dev'
Requires-Dist: pytest>=7.0.0; extra == 'dev'
Requires-Dist: python-dotenv>=1.0.0; extra == 'dev'
Requires-Dist: ruff>=0.1.0; extra == 'dev'
Requires-Dist: scipy-stubs>=1.11.0; extra == 'dev'
Requires-Dist: types-pyyaml>=6.0.0; extra == 'dev'
Requires-Dist: types-requests>=2.31.0; extra == 'dev'
Provides-Extra: docs
Requires-Dist: mkdocs-material>=9.0.0; extra == 'docs'
Requires-Dist: mkdocs>=1.5.0; extra == 'docs'
Requires-Dist: mkdocstrings[python]>=0.24.0; extra == 'docs'
Provides-Extra: notebook
Requires-Dist: ipywidgets>=8.1.5; extra == 'notebook'
Requires-Dist: jupyter-bokeh>=4.0.5; extra == 'notebook'
Requires-Dist: jupyter-server>=2.15.0; extra == 'notebook'
Requires-Dist: jupyter>=1.1.1; extra == 'notebook'
Requires-Dist: requests>=2.31.0; extra == 'notebook'
Provides-Extra: qm
Requires-Dist: pyvisa-py>=0.7.1; extra == 'qm'
Requires-Dist: pyvisa>=1.13.0; extra == 'qm'
Requires-Dist: qm-qua>=1.2.0; extra == 'qm'
Provides-Extra: routines
Requires-Dist: scipy>=1.14.1; extra == 'routines'
Provides-Extra: test
Requires-Dist: pytest-asyncio>=0.21.0; extra == 'test'
Requires-Dist: pytest-cov>=4.0.0; extra == 'test'
Requires-Dist: pytest>=7.0.0; extra == 'test'
Requires-Dist: pyvisa-sim>=0.7.0; extra == 'test'
Requires-Dist: qm-saas>=1.1.5; extra == 'test'
